beta_dia/__init__.py
beta_dia/assemble.py
beta_dia/calib.py
beta_dia/cross.py
beta_dia/dataloader.py
beta_dia/decoy.py
beta_dia/deepmall.py
beta_dia/deepmap.py
beta_dia/fdr.py
beta_dia/fxic.py
beta_dia/library.py
beta_dia/log.py
beta_dia/models.py
beta_dia/param_g.py
beta_dia/polish.py
beta_dia/quant.py
beta_dia/refine.py
beta_dia/scoring.py
beta_dia/tims.py
beta_dia/utils.py
beta_dia/__pycache__/__init__.cpython-39.pyc
beta_dia/alphatims/__init__.py
beta_dia/alphatims/bruker.py
beta_dia/alphatims/utils.py
beta_dia/alphatims/ext/timsdata.dll
beta_dia/alphatims/ext/timsdata.so
beta_dia/dist/__init__.py
beta_dia/dist/main.py
beta_dia/dist/main_core.py
beta_dia/dist/pyarmor_runtime_000000/__init__.py
beta_dia/dist/pyarmor_runtime_000000/linux_x86_64/pyarmor_runtime.so
beta_dia/dist/pyarmor_runtime_000000/windows_x86_64/pyarmor_runtime.pyd
beta_dia/pretrained/deepbig_ys_fast.pt
beta_dia/pretrained/deepcenter_ys_fast.pt
beta_dia-1.1.0.dist-info/LICENSE
beta_dia-1.1.0.dist-info/METADATA
beta_dia-1.1.0.dist-info/WHEEL
beta_dia-1.1.0.dist-info/entry_points.txt
beta_dia-1.1.0.dist-info/top_level.txt
beta_dia-1.1.0.dist-info/RECORD
