Metadata-Version: 2.1
Name: beta-dia
Version: 1.1.0
Summary: A cool project that does something awesome on diaPASEF data.
Home-page: https://github.com/YuAirLab/beta_dia
Author: Song Jian
Author-email: songjian2022@suda.edu.cn
License: Apache
Platform: UNKNOWN
Classifier: Programming Language :: Python :: 3
Classifier: License :: OSI Approved :: Apache Software License
Classifier: Operating System :: OS Independent
Requires-Python: >=3.9
License-File: LICENSE
Requires-Dist: psutil
Requires-Dist: h5py
Requires-Dist: matplotlib
Requires-Dist: networkx
Requires-Dist: numba
Requires-Dist: numpy<2.0.0
Requires-Dist: pandas
Requires-Dist: pyzstd
Requires-Dist: scikit-learn
Requires-Dist: scipy
Requires-Dist: statsmodels
Requires-Dist: pyarrow
